LICENSE
robonomicsinterface/__init__.py
robonomicsinterface/classes/__init__.py
robonomicsinterface/classes/account.py
robonomicsinterface/classes/base.py
robonomicsinterface/classes/chain_utils.py
robonomicsinterface/classes/common_functions.py
robonomicsinterface/classes/datalog.py
robonomicsinterface/classes/digital_twin.py
robonomicsinterface/classes/launch.py
robonomicsinterface/classes/liability.py
robonomicsinterface/classes/pubsub.py
robonomicsinterface/classes/reqres.py
robonomicsinterface/classes/rws.py
robonomicsinterface/classes/service_functions.py
robonomicsinterface/classes/subscriptions.py
robonomicsinterface/constants.py
robonomicsinterface/decorators.py
robonomicsinterface/exceptions.py
robonomicsinterface/robonomics_interface_io.py
robonomicsinterface/types.py
robonomicsinterface/utils.py
robonomics_interface-2.0.0.dist-info/LICENSE
robonomics_interface-2.0.0.dist-info/METADATA
robonomics_interface-2.0.0.dist-info/WHEEL
robonomics_interface-2.0.0.dist-info/entry_points.txt
robonomics_interface-2.0.0.dist-info/RECORD
