Metadata-Version: 2.1
Name: robonomics-interface
Version: 2.0.0
Summary: This is a simple wrapper over polkascan/py-substrate-interface used to facilitate writing code for applications using Robonomics Polkadot Parachain.
Home-page: https://github.com/airalab/robonomics-interface
License: Apache-2.0
Keywords: python3,wrapper,blockchain,substrate,robonomics,pypi-package
Author: Pavel Tarasov
Author-email: p040399@outlook.com
Requires-Python: >=3.8,<4.0
Classifier: License :: OSI Approved :: Apache Software License
Classifier: Operating System :: Unix
Classifier: Programming Language :: Python :: 3
Classifier: Programming Language :: Python :: 3.8
Classifier: Programming Language :: Python :: 3.9
Classifier: Programming Language :: Python :: 3.10
Classifier: Programming Language :: Python :: 3.11
Classifier: Programming Language :: Python :: 3.12
Classifier: Programming Language :: Python :: 3.13
Classifier: Topic :: Scientific/Engineering :: Human Machine Interfaces
Classifier: Topic :: Software Development :: Documentation
Classifier: Topic :: Software Development :: Libraries :: Python Modules
Requires-Dist: click (>=8.0.4,<9.0.0)
Requires-Dist: substrate-interface (>=1.4.0,<2.0)
Project-URL: Bug Tracker, https://github.com/airalab/robonomics-interface/issues
Project-URL: Documentation, https://airalab.github.io/robonomics-interface/
Project-URL: Repository, https://github.com/airalab/robonomics-interface
